mlx_llm/__init__.py
mlx_llm/callbacks/__init__.py
mlx_llm/callbacks/data.py
mlx_llm/callbacks/model.py
mlx_llm/callbacks/stats.py
mlx_llm/chat/__init__.py
mlx_llm/chat/chat.py
mlx_llm/chat/utils.py
mlx_llm/dataset/__init__.py
mlx_llm/dataset/dataset.py
mlx_llm/loader/__init__.py
mlx_llm/loader/loader.py
mlx_llm/lora/__init__.py
mlx_llm/lora/layers.py
mlx_llm/lora/utils.py
mlx_llm/model/__init__.py
mlx_llm/model/_config.py
mlx_llm/model/_factory.py
mlx_llm/model/_registry.py
mlx_llm/model/_utils.py
mlx_llm/model/converter.py
mlx_llm/model/transformer.py
mlx_llm/prompt/__init__.py
mlx_llm/prompt/_base.py
mlx_llm/prompt/gemma.py
mlx_llm/prompt/hermes.py
mlx_llm/prompt/llama.py
mlx_llm/prompt/mistral.py
mlx_llm/prompt/openelm.py
mlx_llm/prompt/phi.py
mlx_llm/tune/__init__.py
mlx_llm/tune/trainer.py
mlx_llm/utils/__init__.py
mlx_llm/utils/config.py
mlx_llm/utils/hf.py
mlx_llm/utils/session.py
mlx_llm/utils/time.py
mlx_llm/utils/weights.py
mlx_llm-1.0.8.dist-info/LICENSE
mlx_llm-1.0.8.dist-info/METADATA
mlx_llm-1.0.8.dist-info/WHEEL
mlx_llm-1.0.8.dist-info/RECORD
