Metadata-Version: 2.3
Name: mlx_llm
Version: 1.0.8
Summary: Large Language Models (LLMs) applications and tools running on Apple Silicon in real-time with Apple MLX
Author: Riccardo Musmeci
Author-email: riccardomusmeci92@gmail.com
Requires-Python: >=3.10,<4.0
Classifier: Programming Language :: Python :: 3
Classifier: Programming Language :: Python :: 3.10
Classifier: Programming Language :: Python :: 3.11
Classifier: Programming Language :: Python :: 3.12
Classifier: Programming Language :: Python :: 3.13
Provides-Extra: dev
Requires-Dist: black[jupyter] (==23.3.0) ; extra == "dev"
Requires-Dist: huggingface-hub
Requires-Dist: matplotlib
Requires-Dist: mlx
Requires-Dist: mypy (==1.2.0) ; extra == "dev"
Requires-Dist: numpy (==1.26.2)
Requires-Dist: protobuf
Requires-Dist: ruff (==0.0.264) ; extra == "dev"
Requires-Dist: safetensors
Requires-Dist: sentencepiece
Requires-Dist: torch
Requires-Dist: tqdm
Requires-Dist: transformers
